tallybot/__init__.py
tallybot/__main__.py
tallybot/agents.py
tallybot/chat.py
tallybot/chat_interface.py
tallybot/exchange.py
tallybot/handlers.py
tallybot/learner.py
tallybot/lookups.py
tallybot/managers.py
tallybot/memories.py
tallybot/plugin.py
tallybot/brain/__init__.py
tallybot/brain/frontal_lobe.py
tallybot/brain/invoicing.py
tallybot/brain/ledger.py
tallybot/brain/main.py
tallybot/brain/reports.py
tallybot/templates/__init__.py
tallybot/templates/invoices/__init__.py
tallybot/templates/invoices/layout.py
tallybot/templates/invoices/schema.py
tallybot-0.0.2.dist-info/METADATA
tallybot-0.0.2.dist-info/WHEEL
tallybot-0.0.2.dist-info/top_level.txt
tallybot-0.0.2.dist-info/RECORD
